[{"caption": "` !\"#$%&'()*+,-./0123456789:;<=>?@ABCDEFGHIJKLMNOPQRSTUVWXYZ[\\]^_`abcdefghijklmnopqrstuvwxyz{|}~` in smallcaps3 font, with 3 spacing and diamond1 decoration", "content": "\u25c4]\u00b7\u2666\u00b7\u00bb    !   \"   #   $   %   &   '   (   )   *   +   ,   -   .   /   \ud835\udff6   \ud835\udff7   \ud835\udff8   \ud835\udff9   \ud835\udffa   \ud835\udffb   \ud835\udffc   \ud835\udffd   \ud835\udffe   \ud835\udfff   :   ;   <   =   >   ?   @   \u1d00   \u0299   \u1d04   \u1d05   \u1d07   \u0493   \u0262   \u029c   \u026a   \u1d0a   \u1d0b   \u029f   \u1d0d   \u0274   \u1d0f   \u1d18   \u01eb   \u0280   s   \u1d1b   \u1d1c   \u1d20   \u1d21   x   \u028f   \u1d22   [   \\   ]   ^   _   `   \u1d00   \u0299   \u1d04   \u1d05   \u1d07   \u0493   \u0262   \u029c   \u026a   \u1d0a   \u1d0b   \u029f   \u1d0d   \u0274   \u1d0f   \u1d18   \u01eb   \u0280   s   \u1d1b   \u1d1c   \u1d20   \u1d21   x   \u028f   \u1d22   {   |   }   ~\u00ab\u00b7\u2666\u00b7[\u25ba", "labels": "smallcaps3 font, 3 spacing, diamond1 decoration", "charsets": "IPA Extensions,Cyrillic,ASCII C0,Phonetic Extensions,Mathematical Alphanumeric Symbols,ASCII C1,Latin Extended-B,Miscellaneous Symbols,Geometric Shapes", "chartypes": "Numbers,Separators,Punctuations,Symbols,Letters"}, {"caption": "` !\"#$%&'()*+,-./0123456789:;<=>?@ABCDEFGHIJKLMNOPQRSTUVWXYZ[\\]^_`abcdefghijklmnopqrstuvwxyz{|}~` in smallcaps3 font, with 2 spacing and diamond1 decoration", "content": "\u25c4]\u00b7\u2666\u00b7\u00bb   !  \"  #  $  %  &  '  (  )  *  +  ,  -  .  /  \ud835\udff6  \ud835\udff7  \ud835\udff8  \ud835\udff9  \ud835\udffa  \ud835\udffb  \ud835\udffc  \ud835\udffd  \ud835\udffe  \ud835\udfff  :  ;  <  =  >  ?  @  \u1d00  \u0299  \u1d04  \u1d05  \u1d07  \u0493  \u0262  \u029c  \u026a  \u1d0a  \u1d0b  \u029f  \u1d0d  \u0274  \u1d0f  \u1d18  \u01eb  \u0280  s  \u1d1b  \u1d1c  \u1d20  \u1d21  x  \u028f  \u1d22  [  \\  ]  ^  _  `  \u1d00  \u0299  \u1d04  \u1d05  \u1d07  \u0493  \u0262  \u029c  \u026a  \u1d0a  \u1d0b  \u029f  \u1d0d  \u0274  \u1d0f  \u1d18  \u01eb  \u0280  s  \u1d1b  \u1d1c  \u1d20  \u1d21  x  \u028f  \u1d22  {  |  }  ~\u00ab\u00b7\u2666\u00b7[\u25ba", "labels": "smallcaps3 font, 2 spacing, diamond1 decoration", "charsets": "IPA Extensions,Cyrillic,ASCII C0,Phonetic Extensions,Mathematical Alphanumeric Symbols,ASCII C1,Latin Extended-B,Miscellaneous Symbols,Geometric Shapes", "chartypes": "Numbers,Separators,Punctuations,Symbols,Letters"}, {"caption": "` !\"#$%&'()*+,-./0123456789:;<=>?@ABCDEFGHIJKLMNOPQRSTUVWXYZ[\\]^_`abcdefghijklmnopqrstuvwxyz{|}~` in smallcaps3 font, with 3 spacing and fancy80 decoration", "content": "\u25e6\u2022\u25cf\u25c9\u273f    !   \"   #   $   %   &   '   (   )   *   +   ,   -   .   /   \ud835\udff6   \ud835\udff7   \ud835\udff8   \ud835\udff9   \ud835\udffa   \ud835\udffb   \ud835\udffc   \ud835\udffd   \ud835\udffe   \ud835\udfff   :   ;   <   =   >   ?   @   \u1d00   \u0299   \u1d04   \u1d05   \u1d07   \u0493   \u0262   \u029c   \u026a   \u1d0a   \u1d0b   \u029f   \u1d0d   \u0274   \u1d0f   \u1d18   \u01eb   \u0280   s   \u1d1b   \u1d1c   \u1d20   \u1d21   x   \u028f   \u1d22   [   \\   ]   ^   _   `   \u1d00   \u0299   \u1d04   \u1d05   \u1d07   \u0493   \u0262   \u029c   \u026a   \u1d0a   \u1d0b   \u029f   \u1d0d   \u0274   \u1d0f   \u1d18   \u01eb   \u0280   s   \u1d1b   \u1d1c   \u1d20   \u1d21   x   \u028f   \u1d22   {   |   }   ~\u273f\u25c9\u25cf\u2022\u25e6", "labels": "smallcaps3 font, 3 spacing, fancy80 decoration", "charsets": "IPA Extensions,Cyrillic,General Punctuation,ASCII C0,Phonetic Extensions,Mathematical Alphanumeric Symbols,Latin Extended-B,Dingbats,Geometric Shapes", "chartypes": "Numbers,Separators,Punctuations,Symbols,Letters"}, {"caption": "` !\"#$%&'()*+,-./0123456789:;<=>?@ABCDEFGHIJKLMNOPQRSTUVWXYZ[\\]^_`abcdefghijklmnopqrstuvwxyz{|}~` in smallcaps3 font, with 2 spacing and fancy80 decoration", "content": "\u25e6\u2022\u25cf\u25c9\u273f   !  \"  #  $  %  &  '  (  )  *  +  ,  -  .  /  \ud835\udff6  \ud835\udff7  \ud835\udff8  \ud835\udff9  \ud835\udffa  \ud835\udffb  \ud835\udffc  \ud835\udffd  \ud835\udffe  \ud835\udfff  :  ;  <  =  >  ?  @  \u1d00  \u0299  \u1d04  \u1d05  \u1d07  \u0493  \u0262  \u029c  \u026a  \u1d0a  \u1d0b  \u029f  \u1d0d  \u0274  \u1d0f  \u1d18  \u01eb  \u0280  s  \u1d1b  \u1d1c  \u1d20  \u1d21  x  \u028f  \u1d22  [  \\  ]  ^  _  `  \u1d00  \u0299  \u1d04  \u1d05  \u1d07  \u0493  \u0262  \u029c  \u026a  \u1d0a  \u1d0b  \u029f  \u1d0d  \u0274  \u1d0f  \u1d18  \u01eb  \u0280  s  \u1d1b  \u1d1c  \u1d20  \u1d21  x  \u028f  \u1d22  {  |  }  ~\u273f\u25c9\u25cf\u2022\u25e6", "labels": "smallcaps3 font, 2 spacing, fancy80 decoration", "charsets": "IPA Extensions,Cyrillic,General Punctuation,ASCII C0,Phonetic Extensions,Mathematical Alphanumeric Symbols,Latin Extended-B,Dingbats,Geometric Shapes", "chartypes": "Numbers,Separators,Punctuations,Symbols,Letters"}, {"caption": "` !\"#$%&'()*+,-./0123456789:;<=>?@ABCDEFGHIJKLMNOPQRSTUVWXYZ[\\]^_`abcdefghijklmnopqrstuvwxyz{|}~` in smallcaps3 font, with 3 spacing and champion1 decoration", "content": "\u25c4[\ud83c\udfc6]\u25ba     !   \"   #   $   %   &   '   (   )   *   +   ,   -   .   /   \ud835\udff6   \ud835\udff7   \ud835\udff8   \ud835\udff9   \ud835\udffa   \ud835\udffb   \ud835\udffc   \ud835\udffd   \ud835\udffe   \ud835\udfff   :   ;   <   =   >   ?   @   \u1d00   \u0299   \u1d04   \u1d05   \u1d07   \u0493   \u0262   \u029c   \u026a   \u1d0a   \u1d0b   \u029f   \u1d0d   \u0274   \u1d0f   \u1d18   \u01eb   \u0280   s   \u1d1b   \u1d1c   \u1d20   \u1d21   x   \u028f   \u1d22   [   \\   ]   ^   _   `   \u1d00   \u0299   \u1d04   \u1d05   \u1d07   \u0493   \u0262   \u029c   \u026a   \u1d0a   \u1d0b   \u029f   \u1d0d   \u0274   \u1d0f   \u1d18   \u01eb   \u0280   s   \u1d1b   \u1d1c   \u1d20   \u1d21   x   \u028f   \u1d22   {   |   }   ~ \u25c4[\ud83e\udd47]\u25ba", "labels": "smallcaps3 font, 3 spacing, champion1 decoration", "charsets": "IPA Extensions,Geometric Shapes,Cyrillic,ASCII C0,Mathematical Alphanumeric Symbols,Latin Extended-B,Miscellaneous Symbols and Pictographs,Supplemental Symbols and Pictographs,Phonetic Extensions", "chartypes": "Numbers,Separators,Punctuations,Symbols,Letters"}, {"caption": "` !\"#$%&'()*+,-./0123456789:;<=>?@ABCDEFGHIJKLMNOPQRSTUVWXYZ[\\]^_`abcdefghijklmnopqrstuvwxyz{|}~` in smallcaps3 font, with 2 spacing and champion1 decoration", "content": "\u25c4[\ud83c\udfc6]\u25ba    !  \"  #  $  %  &  '  (  )  *  +  ,  -  .  /  \ud835\udff6  \ud835\udff7  \ud835\udff8  \ud835\udff9  \ud835\udffa  \ud835\udffb  \ud835\udffc  \ud835\udffd  \ud835\udffe  \ud835\udfff  :  ;  <  =  >  ?  @  \u1d00  \u0299  \u1d04  \u1d05  \u1d07  \u0493  \u0262  \u029c  \u026a  \u1d0a  \u1d0b  \u029f  \u1d0d  \u0274  \u1d0f  \u1d18  \u01eb  \u0280  s  \u1d1b  \u1d1c  \u1d20  \u1d21  x  \u028f  \u1d22  [  \\  ]  ^  _  `  \u1d00  \u0299  \u1d04  \u1d05  \u1d07  \u0493  \u0262  \u029c  \u026a  \u1d0a  \u1d0b  \u029f  \u1d0d  \u0274  \u1d0f  \u1d18  \u01eb  \u0280  s  \u1d1b  \u1d1c  \u1d20  \u1d21  x  \u028f  \u1d22  {  |  }  ~ \u25c4[\ud83e\udd47]\u25ba", "labels": "smallcaps3 font, 2 spacing, champion1 decoration", "charsets": "IPA Extensions,Geometric Shapes,Cyrillic,ASCII C0,Mathematical Alphanumeric Symbols,Latin Extended-B,Miscellaneous Symbols and Pictographs,Supplemental Symbols and Pictographs,Phonetic Extensions", "chartypes": "Numbers,Separators,Punctuations,Symbols,Letters"}, {"caption": "` !\"#$%&'()*+,-./0123456789:;<=>?@ABCDEFGHIJKLMNOPQRSTUVWXYZ[\\]^_`abcdefghijklmnopqrstuvwxyz{|}~` in smallcaps3 font, with 3 spacing and no decoration", "content": "    !   \"   #   $   %   &   '   (   )   *   +   ,   -   .   /   \ud835\udff6   \ud835\udff7   \ud835\udff8   \ud835\udff9   \ud835\udffa   \ud835\udffb   \ud835\udffc   \ud835\udffd   \ud835\udffe   \ud835\udfff   :   ;   <   =   >   ?   @   \u1d00   \u0299   \u1d04   \u1d05   \u1d07   \u0493   \u0262   \u029c   \u026a   \u1d0a   \u1d0b   \u029f   \u1d0d   \u0274   \u1d0f   \u1d18   \u01eb   \u0280   s   \u1d1b   \u1d1c   \u1d20   \u1d21   x   \u028f   \u1d22   [   \\   ]   ^   _   `   \u1d00   \u0299   \u1d04   \u1d05   \u1d07   \u0493   \u0262   \u029c   \u026a   \u1d0a   \u1d0b   \u029f   \u1d0d   \u0274   \u1d0f   \u1d18   \u01eb   \u0280   s   \u1d1b   \u1d1c   \u1d20   \u1d21   x   \u028f   \u1d22   {   |   }   ~", "labels": "smallcaps3 font, 3 spacing, no decoration", "charsets": "IPA Extensions,Cyrillic,ASCII C0,Mathematical Alphanumeric Symbols,Latin Extended-B,Phonetic Extensions", "chartypes": "Numbers,Separators,Punctuations,Symbols,Letters"}, {"caption": "` !\"#$%&'()*+,-./0123456789:;<=>?@ABCDEFGHIJKLMNOPQRSTUVWXYZ[\\]^_`abcdefghijklmnopqrstuvwxyz{|}~` in smallcaps3 font, with 2 spacing and no decoration", "content": "   !  \"  #  $  %  &  '  (  )  *  +  ,  -  .  /  \ud835\udff6  \ud835\udff7  \ud835\udff8  \ud835\udff9  \ud835\udffa  \ud835\udffb  \ud835\udffc  \ud835\udffd  \ud835\udffe  \ud835\udfff  :  ;  <  =  >  ?  @  \u1d00  \u0299  \u1d04  \u1d05  \u1d07  \u0493  \u0262  \u029c  \u026a  \u1d0a  \u1d0b  \u029f  \u1d0d  \u0274  \u1d0f  \u1d18  \u01eb  \u0280  s  \u1d1b  \u1d1c  \u1d20  \u1d21  x  \u028f  \u1d22  [  \\  ]  ^  _  `  \u1d00  \u0299  \u1d04  \u1d05  \u1d07  \u0493  \u0262  \u029c  \u026a  \u1d0a  \u1d0b  \u029f  \u1d0d  \u0274  \u1d0f  \u1d18  \u01eb  \u0280  s  \u1d1b  \u1d1c  \u1d20  \u1d21  x  \u028f  \u1d22  {  |  }  ~", "labels": "smallcaps3 font, 2 spacing, no decoration", "charsets": "IPA Extensions,Cyrillic,ASCII C0,Mathematical Alphanumeric Symbols,Latin Extended-B,Phonetic Extensions", "chartypes": "Numbers,Separators,Punctuations,Symbols,Letters"}, {"caption": "`Lorem ipsum dolor sit amet, consectetur adipiscing elit.` in smallcaps3 font, with 0 spacing and wave7 decoration", "content": "(\u00af`\u00b7._(\u00af`\u00b7._(\u00af`\u00b7._\u029f\u1d0f\u0280\u1d07\u1d0d \u026a\u1d18s\u1d1c\u1d0d \u1d05\u1d0f\u029f\u1d0f\u0280 s\u026a\u1d1b \u1d00\u1d0d\u1d07\u1d1b, \u1d04\u1d0f\u0274s\u1d07\u1d04\u1d1b\u1d07\u1d1b\u1d1c\u0280 \u1d00\u1d05\u026a\u1d18\u026as\u1d04\u026a\u0274\u0262 \u1d07\u029f\u026a\u1d1b._.\u00b7\u00af)_.\u00b7\u00af)_.\u00b7\u00af)", "labels": "smallcaps3 font, 0 spacing, wave7 decoration", "charsets": "ASCII C1,ASCII C0,Phonetic Extensions,IPA Extensions", "chartypes": "Letters,Symbols,Separators,Punctuations"}, {"caption": "`Lorem ipsum dolor sit amet, consectetur adipiscing elit.` in smallcaps3 font, with 1 spacing and wave7 decoration", "content": "(\u00af`\u00b7._(\u00af`\u00b7._(\u00af`\u00b7._\u029f \u1d0f \u0280 \u1d07 \u1d0d   \u026a \u1d18 s \u1d1c \u1d0d   \u1d05 \u1d0f \u029f \u1d0f \u0280   s \u026a \u1d1b   \u1d00 \u1d0d \u1d07 \u1d1b ,   \u1d04 \u1d0f \u0274 s \u1d07 \u1d04 \u1d1b \u1d07 \u1d1b \u1d1c \u0280   \u1d00 \u1d05 \u026a \u1d18 \u026a s \u1d04 \u026a \u0274 \u0262   \u1d07 \u029f \u026a \u1d1b ._.\u00b7\u00af)_.\u00b7\u00af)_.\u00b7\u00af)", "labels": "smallcaps3 font, 1 spacing, wave7 decoration", "charsets": "ASCII C1,ASCII C0,Phonetic Extensions,IPA Extensions", "chartypes": "Letters,Symbols,Separators,Punctuations"}, {"caption": "`Lorem ipsum dolor sit amet, consectetur adipiscing elit.` in smallcaps3 font, with 0 spacing and fancy20 decoration", "content": "\u25cf\u25ac\u25ac\u25ac\u0e51\u06e9\u06e9\u0e51\u25ac\u25ac\u25ac\u25cf\u029f\u1d0f\u0280\u1d07\u1d0d \u026a\u1d18s\u1d1c\u1d0d \u1d05\u1d0f\u029f\u1d0f\u0280 s\u026a\u1d1b \u1d00\u1d0d\u1d07\u1d1b, \u1d04\u1d0f\u0274s\u1d07\u1d04\u1d1b\u1d07\u1d1b\u1d1c\u0280 \u1d00\u1d05\u026a\u1d18\u026as\u1d04\u026a\u0274\u0262 \u1d07\u029f\u026a\u1d1b.\u25cf\u25ac\u25ac\u25ac\u0e51\u06e9\u06e9\u0e51\u25ac\u25ac\u25ac\u25cf", "labels": "smallcaps3 font, 0 spacing, fancy20 decoration", "charsets": "IPA Extensions,Geometric Shapes,Arabic,ASCII C0,Thai,Phonetic Extensions", "chartypes": "Numbers,Separators,Punctuations,Symbols,Letters"}, {"caption": "`Lorem ipsum dolor sit amet, consectetur adipiscing elit.` in smallcaps3 font, with 1 spacing and fancy20 decoration", "content": "\u25cf\u25ac\u25ac\u25ac\u0e51\u06e9\u06e9\u0e51\u25ac\u25ac\u25ac\u25cf\u029f \u1d0f \u0280 \u1d07 \u1d0d   \u026a \u1d18 s \u1d1c \u1d0d   \u1d05 \u1d0f \u029f \u1d0f \u0280   s \u026a \u1d1b   \u1d00 \u1d0d \u1d07 \u1d1b ,   \u1d04 \u1d0f \u0274 s \u1d07 \u1d04 \u1d1b \u1d07 \u1d1b \u1d1c \u0280   \u1d00 \u1d05 \u026a \u1d18 \u026a s \u1d04 \u026a \u0274 \u0262   \u1d07 \u029f \u026a \u1d1b .\u25cf\u25ac\u25ac\u25ac\u0e51\u06e9\u06e9\u0e51\u25ac\u25ac\u25ac\u25cf", "labels": "smallcaps3 font, 1 spacing, fancy20 decoration", "charsets": "IPA Extensions,Arabic,ASCII C0,Phonetic Extensions,Thai,Geometric Shapes", "chartypes": "Numbers,Separators,Punctuations,Symbols,Letters"}, {"caption": "`Lorem ipsum dolor sit amet, consectetur adipiscing elit.` in smallcaps3 font, with 0 spacing and happy1 decoration", "content": "o\u0361\u0361\u0361\u0361\u0361\u0361\u0361\u0361\u0361\u0361\u0361\u0361\u0361\u0361\u256e(\uff61\u275b\u1d17\u275b\uff61)\u256do\u0361\u0361\u0361\u0361\u0361\u0361\u0361\u0361\u0361\u0361\u0361\u0361\u0361\u0361\u029f\u1d0f\u0280\u1d07\u1d0d \u026a\u1d18s\u1d1c\u1d0d \u1d05\u1d0f\u029f\u1d0f\u0280 s\u026a\u1d1b \u1d00\u1d0d\u1d07\u1d1b, \u1d04\u1d0f\u0274s\u1d07\u1d04\u1d1b\u1d07\u1d1b\u1d1c\u0280 \u1d00\u1d05\u026a\u1d18\u026as\u1d04\u026a\u0274\u0262 \u1d07\u029f\u026a\u1d1b.o\u0361\u0361\u0361\u0361\u0361\u0361\u0361\u0361\u0361\u0361\u0361\u0361\u0361\u0361\u256e(\uff61\u275b\u1d17\u275b\uff61)\u256do\u0361\u0361\u0361\u0361\u0361\u0361\u0361\u0361\u0361\u0361\u0361\u0361\u0361\u0361", "labels": "smallcaps3 font, 0 spacing, happy1 decoration", "charsets": "IPA Extensions,ASCII C0,Halfwidth and Fullwidth Forms,Combining Diacritical Marks,Box Drawing,Dingbats,Phonetic Extensions", "chartypes": "Separators,Punctuations,Marks,Symbols,Letters"}, {"caption": "`Lorem ipsum dolor sit amet, consectetur adipiscing elit.` in smallcaps3 font, with 1 spacing and happy1 decoration", "content": "o\u0361\u0361\u0361\u0361\u0361\u0361\u0361\u0361\u0361\u0361\u0361\u0361\u0361\u0361\u256e(\uff61\u275b\u1d17\u275b\uff61)\u256do\u0361\u0361\u0361\u0361\u0361\u0361\u0361\u0361\u0361\u0361\u0361\u0361\u0361\u0361\u029f \u1d0f \u0280 \u1d07 \u1d0d   \u026a \u1d18 s \u1d1c \u1d0d   \u1d05 \u1d0f \u029f \u1d0f \u0280   s \u026a \u1d1b   \u1d00 \u1d0d \u1d07 \u1d1b ,   \u1d04 \u1d0f \u0274 s \u1d07 \u1d04 \u1d1b \u1d07 \u1d1b \u1d1c \u0280   \u1d00 \u1d05 \u026a \u1d18 \u026a s \u1d04 \u026a \u0274 \u0262   \u1d07 \u029f \u026a \u1d1b .o\u0361\u0361\u0361\u0361\u0361\u0361\u0361\u0361\u0361\u0361\u0361\u0361\u0361\u0361\u256e(\uff61\u275b\u1d17\u275b\uff61)\u256do\u0361\u0361\u0361\u0361\u0361\u0361\u0361\u0361\u0361\u0361\u0361\u0361\u0361\u0361", "labels": "smallcaps3 font, 1 spacing, happy1 decoration", "charsets": "IPA Extensions,ASCII C0,Halfwidth and Fullwidth Forms,Combining Diacritical Marks,Box Drawing,Dingbats,Phonetic Extensions", "chartypes": "Separators,Punctuations,Marks,Symbols,Letters"}, {"caption": "`Lorem ipsum dolor sit amet, consectetur adipiscing elit.` in smallcaps3 font, with 0 spacing and no decoration", "content": "\u029f\u1d0f\u0280\u1d07\u1d0d \u026a\u1d18s\u1d1c\u1d0d \u1d05\u1d0f\u029f\u1d0f\u0280 s\u026a\u1d1b \u1d00\u1d0d\u1d07\u1d1b, \u1d04\u1d0f\u0274s\u1d07\u1d04\u1d1b\u1d07\u1d1b\u1d1c\u0280 \u1d00\u1d05\u026a\u1d18\u026as\u1d04\u026a\u0274\u0262 \u1d07\u029f\u026a\u1d1b.", "labels": "smallcaps3 font, 0 spacing, no decoration", "charsets": "IPA Extensions,ASCII C0,Phonetic Extensions", "chartypes": "Letters,Separators,Punctuations"}, {"caption": "`Lorem ipsum dolor sit amet, consectetur adipiscing elit.` in smallcaps3 font, with 1 spacing and no decoration", "content": "\u029f \u1d0f \u0280 \u1d07 \u1d0d   \u026a \u1d18 s \u1d1c \u1d0d   \u1d05 \u1d0f \u029f \u1d0f \u0280   s \u026a \u1d1b   \u1d00 \u1d0d \u1d07 \u1d1b ,   \u1d04 \u1d0f \u0274 s \u1d07 \u1d04 \u1d1b \u1d07 \u1d1b \u1d1c \u0280   \u1d00 \u1d05 \u026a \u1d18 \u026a s \u1d04 \u026a \u0274 \u0262   \u1d07 \u029f \u026a \u1d1b .", "labels": "smallcaps3 font, 1 spacing, no decoration", "charsets": "IPA Extensions,ASCII C0,Phonetic Extensions", "chartypes": "Letters,Separators,Punctuations"}, {"caption": "`os.path.realpath(\n    os.path.join(os.path.dirname(__file__),\n    \"../\",\n    \"datasets/graffiti/asciiart.json\"))` in smallcaps3 font, with 0 spacing and heart1 decoration", "content": "~~<\ud83d\udc9a>~~\u1d0fs.\u1d18\u1d00\u1d1b\u029c.\u0280\u1d07\u1d00\u029f\u1d18\u1d00\u1d1b\u029c(\n    \u1d0fs.\u1d18\u1d00\u1d1b\u029c.\u1d0a\u1d0f\u026a\u0274(\u1d0fs.\u1d18\u1d00\u1d1b\u029c.\u1d05\u026a\u0280\u0274\u1d00\u1d0d\u1d07(__\u0493\u026a\u029f\u1d07__),\n    \"../\",\n    \"\u1d05\u1d00\u1d1b\u1d00s\u1d07\u1d1bs/\u0262\u0280\u1d00\u0493\u0493\u026a\u1d1b\u026a/\u1d00s\u1d04\u026a\u026a\u1d00\u0280\u1d1b.\u1d0as\u1d0f\u0274\"))~~<\ud83d\udc9a>~~", "labels": "smallcaps3 font, 0 spacing, heart1 decoration", "charsets": "IPA Extensions,Cyrillic,ASCII C0,Miscellaneous Symbols and Pictographs,Phonetic Extensions", "chartypes": "Separators,Punctuations,Symbols,Letters,Others"}, {"caption": "`os.path.realpath(\n    os.path.join(os.path.dirname(__file__),\n    \"../\",\n    \"datasets/graffiti/asciiart.json\"))` in smallcaps3 font, with 1 spacing and heart1 decoration", "content": "~~<\ud83d\udc9a>~~\u1d0f s . \u1d18 \u1d00 \u1d1b \u029c . \u0280 \u1d07 \u1d00 \u029f \u1d18 \u1d00 \u1d1b \u029c ( \n         \u1d0f s . \u1d18 \u1d00 \u1d1b \u029c . \u1d0a \u1d0f \u026a \u0274 ( \u1d0f s . \u1d18 \u1d00 \u1d1b \u029c . \u1d05 \u026a \u0280 \u0274 \u1d00 \u1d0d \u1d07 ( _ _ \u0493 \u026a \u029f \u1d07 _ _ ) , \n         \" . . / \" , \n         \" \u1d05 \u1d00 \u1d1b \u1d00 s \u1d07 \u1d1b s / \u0262 \u0280 \u1d00 \u0493 \u0493 \u026a \u1d1b \u026a / \u1d00 s \u1d04 \u026a \u026a \u1d00 \u0280 \u1d1b . \u1d0a s \u1d0f \u0274 \" ) )~~<\ud83d\udc9a>~~", "labels": "smallcaps3 font, 1 spacing, heart1 decoration", "charsets": "IPA Extensions,Cyrillic,ASCII C0,Miscellaneous Symbols and Pictographs,Phonetic Extensions", "chartypes": "Separators,Punctuations,Symbols,Letters,Others"}, {"caption": "`os.path.realpath(\n    os.path.join(os.path.dirname(__file__),\n    \"../\",\n    \"datasets/graffiti/asciiart.json\"))` in smallcaps3 font, with 0 spacing and egypt1 decoration", "content": "\u256d\u20aa\u20aa\u20aa\u1d0fs.\u1d18\u1d00\u1d1b\u029c.\u0280\u1d07\u1d00\u029f\u1d18\u1d00\u1d1b\u029c(\n    \u1d0fs.\u1d18\u1d00\u1d1b\u029c.\u1d0a\u1d0f\u026a\u0274(\u1d0fs.\u1d18\u1d00\u1d1b\u029c.\u1d05\u026a\u0280\u0274\u1d00\u1d0d\u1d07(__\u0493\u026a\u029f\u1d07__),\n    \"../\",\n    \"\u1d05\u1d00\u1d1b\u1d00s\u1d07\u1d1bs/\u0262\u0280\u1d00\u0493\u0493\u026a\u1d1b\u026a/\u1d00s\u1d04\u026a\u026a\u1d00\u0280\u1d1b.\u1d0as\u1d0f\u0274\"))\u20aa\u20aa\u20aa\u256e", "labels": "smallcaps3 font, 0 spacing, egypt1 decoration", "charsets": "IPA Extensions,Cyrillic,ASCII C0,Box Drawing,Currency Symbols,Phonetic Extensions", "chartypes": "Separators,Punctuations,Symbols,Letters,Others"}, {"caption": "`os.path.realpath(\n    os.path.join(os.path.dirname(__file__),\n    \"../\",\n    \"datasets/graffiti/asciiart.json\"))` in smallcaps3 font, with 1 spacing and egypt1 decoration", "content": "\u256d\u20aa\u20aa\u20aa\u1d0f s . \u1d18 \u1d00 \u1d1b \u029c . \u0280 \u1d07 \u1d00 \u029f \u1d18 \u1d00 \u1d1b \u029c ( \n         \u1d0f s . \u1d18 \u1d00 \u1d1b \u029c . \u1d0a \u1d0f \u026a \u0274 ( \u1d0f s . \u1d18 \u1d00 \u1d1b \u029c . \u1d05 \u026a \u0280 \u0274 \u1d00 \u1d0d \u1d07 ( _ _ \u0493 \u026a \u029f \u1d07 _ _ ) , \n         \" . . / \" , \n         \" \u1d05 \u1d00 \u1d1b \u1d00 s \u1d07 \u1d1b s / \u0262 \u0280 \u1d00 \u0493 \u0493 \u026a \u1d1b \u026a / \u1d00 s \u1d04 \u026a \u026a \u1d00 \u0280 \u1d1b . \u1d0a s \u1d0f \u0274 \" ) )\u20aa\u20aa\u20aa\u256e", "labels": "smallcaps3 font, 1 spacing, egypt1 decoration", "charsets": "IPA Extensions,Cyrillic,ASCII C0,Box Drawing,Currency Symbols,Phonetic Extensions", "chartypes": "Separators,Punctuations,Symbols,Letters,Others"}, {"caption": "`os.path.realpath(\n    os.path.join(os.path.dirname(__file__),\n    \"../\",\n    \"datasets/graffiti/asciiart.json\"))` in smallcaps3 font, with 0 spacing and diamond1 decoration", "content": "\u25c4]\u00b7\u2666\u00b7\u00bb\u1d0fs.\u1d18\u1d00\u1d1b\u029c.\u0280\u1d07\u1d00\u029f\u1d18\u1d00\u1d1b\u029c(\n    \u1d0fs.\u1d18\u1d00\u1d1b\u029c.\u1d0a\u1d0f\u026a\u0274(\u1d0fs.\u1d18\u1d00\u1d1b\u029c.\u1d05\u026a\u0280\u0274\u1d00\u1d0d\u1d07(__\u0493\u026a\u029f\u1d07__),\n    \"../\",\n    \"\u1d05\u1d00\u1d1b\u1d00s\u1d07\u1d1bs/\u0262\u0280\u1d00\u0493\u0493\u026a\u1d1b\u026a/\u1d00s\u1d04\u026a\u026a\u1d00\u0280\u1d1b.\u1d0as\u1d0f\u0274\"))\u00ab\u00b7\u2666\u00b7[\u25ba", "labels": "smallcaps3 font, 0 spacing, diamond1 decoration", "charsets": "IPA Extensions,Geometric Shapes,Cyrillic,ASCII C0,ASCII C1,Miscellaneous Symbols,Phonetic Extensions", "chartypes": "Separators,Punctuations,Symbols,Letters,Others"}, {"caption": "`os.path.realpath(\n    os.path.join(os.path.dirname(__file__),\n    \"../\",\n    \"datasets/graffiti/asciiart.json\"))` in smallcaps3 font, with 1 spacing and diamond1 decoration", "content": "\u25c4]\u00b7\u2666\u00b7\u00bb\u1d0f s . \u1d18 \u1d00 \u1d1b \u029c . \u0280 \u1d07 \u1d00 \u029f \u1d18 \u1d00 \u1d1b \u029c ( \n         \u1d0f s . \u1d18 \u1d00 \u1d1b \u029c . \u1d0a \u1d0f \u026a \u0274 ( \u1d0f s . \u1d18 \u1d00 \u1d1b \u029c . \u1d05 \u026a \u0280 \u0274 \u1d00 \u1d0d \u1d07 ( _ _ \u0493 \u026a \u029f \u1d07 _ _ ) , \n         \" . . / \" , \n         \" \u1d05 \u1d00 \u1d1b \u1d00 s \u1d07 \u1d1b s / \u0262 \u0280 \u1d00 \u0493 \u0493 \u026a \u1d1b \u026a / \u1d00 s \u1d04 \u026a \u026a \u1d00 \u0280 \u1d1b . \u1d0a s \u1d0f \u0274 \" ) )\u00ab\u00b7\u2666\u00b7[\u25ba", "labels": "smallcaps3 font, 1 spacing, diamond1 decoration", "charsets": "IPA Extensions,Geometric Shapes,Cyrillic,ASCII C0,ASCII C1,Miscellaneous Symbols,Phonetic Extensions", "chartypes": "Separators,Punctuations,Symbols,Letters,Others"}, {"caption": "`os.path.realpath(\n    os.path.join(os.path.dirname(__file__),\n    \"../\",\n    \"datasets/graffiti/asciiart.json\"))` in smallcaps3 font, with 0 spacing and no decoration", "content": "\u1d0fs.\u1d18\u1d00\u1d1b\u029c.\u0280\u1d07\u1d00\u029f\u1d18\u1d00\u1d1b\u029c(\n    \u1d0fs.\u1d18\u1d00\u1d1b\u029c.\u1d0a\u1d0f\u026a\u0274(\u1d0fs.\u1d18\u1d00\u1d1b\u029c.\u1d05\u026a\u0280\u0274\u1d00\u1d0d\u1d07(__\u0493\u026a\u029f\u1d07__),\n    \"../\",\n    \"\u1d05\u1d00\u1d1b\u1d00s\u1d07\u1d1bs/\u0262\u0280\u1d00\u0493\u0493\u026a\u1d1b\u026a/\u1d00s\u1d04\u026a\u026a\u1d00\u0280\u1d1b.\u1d0as\u1d0f\u0274\"))", "labels": "smallcaps3 font, 0 spacing, no decoration", "charsets": "IPA Extensions,ASCII C0,Cyrillic,Phonetic Extensions", "chartypes": "Others,Letters,Separators,Punctuations"}, {"caption": "`os.path.realpath(\n    os.path.join(os.path.dirname(__file__),\n    \"../\",\n    \"datasets/graffiti/asciiart.json\"))` in smallcaps3 font, with 1 spacing and no decoration", "content": "\u1d0f s . \u1d18 \u1d00 \u1d1b \u029c . \u0280 \u1d07 \u1d00 \u029f \u1d18 \u1d00 \u1d1b \u029c ( \n         \u1d0f s . \u1d18 \u1d00 \u1d1b \u029c . \u1d0a \u1d0f \u026a \u0274 ( \u1d0f s . \u1d18 \u1d00 \u1d1b \u029c . \u1d05 \u026a \u0280 \u0274 \u1d00 \u1d0d \u1d07 ( _ _ \u0493 \u026a \u029f \u1d07 _ _ ) , \n         \" . . / \" , \n         \" \u1d05 \u1d00 \u1d1b \u1d00 s \u1d07 \u1d1b s / \u0262 \u0280 \u1d00 \u0493 \u0493 \u026a \u1d1b \u026a / \u1d00 s \u1d04 \u026a \u026a \u1d00 \u0280 \u1d1b . \u1d0a s \u1d0f \u0274 \" ) )", "labels": "smallcaps3 font, 1 spacing, no decoration", "charsets": "IPA Extensions,ASCII C0,Cyrillic,Phonetic Extensions", "chartypes": "Others,Letters,Separators,Punctuations"}, {"caption": "`L\u2019art ASCII consiste \u00e0 r\u00e9aliser des images uniquement \u00e0 l'aide des lettres et caract\u00e8res sp\u00e9ciaux contenus dans le code ASCII.` in smallcaps3 font, with 3 spacing and egypt1 decoration", "content": "\u256d\u20aa\u20aa\u20aa\u029f      \u1d00   \u0280   \u1d1b       \u1d00   s   \u1d04   \u026a   \u026a       \u1d04   \u1d0f   \u0274   s   \u026a   s   \u1d1b   \u1d07              \u0280      \u1d00   \u029f   \u026a   s   \u1d07   \u0280       \u1d05   \u1d07   s       \u026a   \u1d0d   \u1d00   \u0262   \u1d07   s       \u1d1c   \u0274   \u026a   \u01eb   \u1d1c   \u1d07   \u1d0d   \u1d07   \u0274   \u1d1b              \u029f   '   \u1d00   \u026a   \u1d05   \u1d07       \u1d05   \u1d07   s       \u029f   \u1d07   \u1d1b   \u1d1b   \u0280   \u1d07   s       \u1d07   \u1d1b       \u1d04   \u1d00   \u0280   \u1d00   \u1d04   \u1d1b      \u0280   \u1d07   s       s   \u1d18      \u1d04   \u026a   \u1d00   \u1d1c   x       \u1d04   \u1d0f   \u0274   \u1d1b   \u1d07   \u0274   \u1d1c   s       \u1d05   \u1d00   \u0274   s       \u029f   \u1d07       \u1d04   \u1d0f   \u1d05   \u1d07       \u1d00   s   \u1d04   \u026a   \u026a   .\u20aa\u20aa\u20aa\u256e", "labels": "smallcaps3 font, 3 spacing, egypt1 decoration", "charsets": "IPA Extensions,ASCII C0,Latin Extended-B,Box Drawing,Currency Symbols,Phonetic Extensions", "chartypes": "Punctuations,Letters,Separators,Symbols"}, {"caption": "`L\u2019art ASCII consiste \u00e0 r\u00e9aliser des images uniquement \u00e0 l'aide des lettres et caract\u00e8res sp\u00e9ciaux contenus dans le code ASCII.` in smallcaps3 font, with 0 spacing and egypt1 decoration", "content": "\u256d\u20aa\u20aa\u20aa\u029f\u1d00\u0280\u1d1b \u1d00s\u1d04\u026a\u026a \u1d04\u1d0f\u0274s\u026as\u1d1b\u1d07  \u0280\u1d00\u029f\u026as\u1d07\u0280 \u1d05\u1d07s \u026a\u1d0d\u1d00\u0262\u1d07s \u1d1c\u0274\u026a\u01eb\u1d1c\u1d07\u1d0d\u1d07\u0274\u1d1b  \u029f'\u1d00\u026a\u1d05\u1d07 \u1d05\u1d07s \u029f\u1d07\u1d1b\u1d1b\u0280\u1d07s \u1d07\u1d1b \u1d04\u1d00\u0280\u1d00\u1d04\u1d1b\u0280\u1d07s s\u1d18\u1d04\u026a\u1d00\u1d1cx \u1d04\u1d0f\u0274\u1d1b\u1d07\u0274\u1d1cs \u1d05\u1d00\u0274s \u029f\u1d07 \u1d04\u1d0f\u1d05\u1d07 \u1d00s\u1d04\u026a\u026a.\u20aa\u20aa\u20aa\u256e", "labels": "smallcaps3 font, 0 spacing, egypt1 decoration", "charsets": "IPA Extensions,ASCII C0,Latin Extended-B,Box Drawing,Currency Symbols,Phonetic Extensions", "chartypes": "Punctuations,Letters,Separators,Symbols"}, {"caption": "`L\u2019art ASCII consiste \u00e0 r\u00e9aliser des images uniquement \u00e0 l'aide des lettres et caract\u00e8res sp\u00e9ciaux contenus dans le code ASCII.` in smallcaps3 font, with 3 spacing and fancy3 decoration", "content": "\u0387\u0660\u2022\u25cf\u2665 \u01b8\u0335\u0321\u04dc\u0335\u0328\u0304\u01b7 \u2665\u25cf\u2022\u0660\u0387\u02d9\u029f      \u1d00   \u0280   \u1d1b       \u1d00   s   \u1d04   \u026a   \u026a       \u1d04   \u1d0f   \u0274   s   \u026a   s   \u1d1b   \u1d07              \u0280      \u1d00   \u029f   \u026a   s   \u1d07   \u0280       \u1d05   \u1d07   s       \u026a   \u1d0d   \u1d00   \u0262   \u1d07   s       \u1d1c   \u0274   \u026a   \u01eb   \u1d1c   \u1d07   \u1d0d   \u1d07   \u0274   \u1d1b              \u029f   '   \u1d00   \u026a   \u1d05   \u1d07       \u1d05   \u1d07   s       \u029f   \u1d07   \u1d1b   \u1d1b   \u0280   \u1d07   s       \u1d07   \u1d1b       \u1d04   \u1d00   \u0280   \u1d00   \u1d04   \u1d1b      \u0280   \u1d07   s       s   \u1d18      \u1d04   \u026a   \u1d00   \u1d1c   x       \u1d04   \u1d0f   \u0274   \u1d1b   \u1d07   \u0274   \u1d1c   s       \u1d05   \u1d00   \u0274   s       \u029f   \u1d07       \u1d04   \u1d0f   \u1d05   \u1d07       \u1d00   s   \u1d04   \u026a   \u026a   .\u02d9\u0387\u0660\u2022\u25cf\u2665 \u01b8\u0335\u0321\u04dc\u0335\u0328\u0304\u01b7 \u2665\u25cf\u2022\u0660\u0387\u02d9", "labels": "smallcaps3 font, 3 spacing, fancy3 decoration", "charsets": "IPA Extensions,Arabic,General Punctuation,ASCII C0,Cyrillic,Phonetic Extensions,Combining Diacritical Marks,Latin Extended-B,Miscellaneous Symbols,Greek and Coptic,Spacing Modifier Letters,Geometric Shapes", "chartypes": "Numbers,Separators,Punctuations,Marks,Symbols,Letters"}, {"caption": "`L\u2019art ASCII consiste \u00e0 r\u00e9aliser des images uniquement \u00e0 l'aide des lettres et caract\u00e8res sp\u00e9ciaux contenus dans le code ASCII.` in smallcaps3 font, with 0 spacing and fancy3 decoration", "content": "\u0387\u0660\u2022\u25cf\u2665 \u01b8\u0335\u0321\u04dc\u0335\u0328\u0304\u01b7 \u2665\u25cf\u2022\u0660\u0387\u02d9\u029f\u1d00\u0280\u1d1b \u1d00s\u1d04\u026a\u026a \u1d04\u1d0f\u0274s\u026as\u1d1b\u1d07  \u0280\u1d00\u029f\u026as\u1d07\u0280 \u1d05\u1d07s \u026a\u1d0d\u1d00\u0262\u1d07s \u1d1c\u0274\u026a\u01eb\u1d1c\u1d07\u1d0d\u1d07\u0274\u1d1b  \u029f'\u1d00\u026a\u1d05\u1d07 \u1d05\u1d07s \u029f\u1d07\u1d1b\u1d1b\u0280\u1d07s \u1d07\u1d1b \u1d04\u1d00\u0280\u1d00\u1d04\u1d1b\u0280\u1d07s s\u1d18\u1d04\u026a\u1d00\u1d1cx \u1d04\u1d0f\u0274\u1d1b\u1d07\u0274\u1d1cs \u1d05\u1d00\u0274s \u029f\u1d07 \u1d04\u1d0f\u1d05\u1d07 \u1d00s\u1d04\u026a\u026a.\u02d9\u0387\u0660\u2022\u25cf\u2665 \u01b8\u0335\u0321\u04dc\u0335\u0328\u0304\u01b7 \u2665\u25cf\u2022\u0660\u0387\u02d9", "labels": "smallcaps3 font, 0 spacing, fancy3 decoration", "charsets": "IPA Extensions,Arabic,General Punctuation,ASCII C0,Cyrillic,Phonetic Extensions,Combining Diacritical Marks,Latin Extended-B,Miscellaneous Symbols,Greek and Coptic,Spacing Modifier Letters,Geometric Shapes", "chartypes": "Numbers,Separators,Punctuations,Marks,Symbols,Letters"}, {"caption": "`L\u2019art ASCII consiste \u00e0 r\u00e9aliser des images uniquement \u00e0 l'aide des lettres et caract\u00e8res sp\u00e9ciaux contenus dans le code ASCII.` in smallcaps3 font, with 3 spacing and star19 decoration", "content": "\u066d\u22b9\u00b0\u2a33\u00b0\u00b7..\u00b7\u00b0\u2a33\u00b0\u029f      \u1d00   \u0280   \u1d1b       \u1d00   s   \u1d04   \u026a   \u026a       \u1d04   \u1d0f   \u0274   s   \u026a   s   \u1d1b   \u1d07              \u0280      \u1d00   \u029f   \u026a   s   \u1d07   \u0280       \u1d05   \u1d07   s       \u026a   \u1d0d   \u1d00   \u0262   \u1d07   s       \u1d1c   \u0274   \u026a   \u01eb   \u1d1c   \u1d07   \u1d0d   \u1d07   \u0274   \u1d1b              \u029f   '   \u1d00   \u026a   \u1d05   \u1d07       \u1d05   \u1d07   s       \u029f   \u1d07   \u1d1b   \u1d1b   \u0280   \u1d07   s       \u1d07   \u1d1b       \u1d04   \u1d00   \u0280   \u1d00   \u1d04   \u1d1b      \u0280   \u1d07   s       s   \u1d18      \u1d04   \u026a   \u1d00   \u1d1c   x       \u1d04   \u1d0f   \u0274   \u1d1b   \u1d07   \u0274   \u1d1c   s       \u1d05   \u1d00   \u0274   s       \u029f   \u1d07       \u1d04   \u1d0f   \u1d05   \u1d07       \u1d00   s   \u1d04   \u026a   \u026a   .\u00b0\u2a33\u00b0\u00b7..\u00b7\u00b0\u2a33\u00b0\u22b9\u066d", "labels": "smallcaps3 font, 3 spacing, star19 decoration", "charsets": "Supplemental Mathematical Operators,IPA Extensions,Mathematical Operators,Arabic,ASCII C0,ASCII C1,Latin Extended-B,Phonetic Extensions", "chartypes": "Letters,Symbols,Separators,Punctuations"}, {"caption": "`L\u2019art ASCII consiste \u00e0 r\u00e9aliser des images uniquement \u00e0 l'aide des lettres et caract\u00e8res sp\u00e9ciaux contenus dans le code ASCII.` in smallcaps3 font, with 0 spacing and star19 decoration", "content": "\u066d\u22b9\u00b0\u2a33\u00b0\u00b7..\u00b7\u00b0\u2a33\u00b0\u029f\u1d00\u0280\u1d1b \u1d00s\u1d04\u026a\u026a \u1d04\u1d0f\u0274s\u026as\u1d1b\u1d07  \u0280\u1d00\u029f\u026as\u1d07\u0280 \u1d05\u1d07s \u026a\u1d0d\u1d00\u0262\u1d07s \u1d1c\u0274\u026a\u01eb\u1d1c\u1d07\u1d0d\u1d07\u0274\u1d1b  \u029f'\u1d00\u026a\u1d05\u1d07 \u1d05\u1d07s \u029f\u1d07\u1d1b\u1d1b\u0280\u1d07s \u1d07\u1d1b \u1d04\u1d00\u0280\u1d00\u1d04\u1d1b\u0280\u1d07s s\u1d18\u1d04\u026a\u1d00\u1d1cx \u1d04\u1d0f\u0274\u1d1b\u1d07\u0274\u1d1cs \u1d05\u1d00\u0274s \u029f\u1d07 \u1d04\u1d0f\u1d05\u1d07 \u1d00s\u1d04\u026a\u026a.\u00b0\u2a33\u00b0\u00b7..\u00b7\u00b0\u2a33\u00b0\u22b9\u066d", "labels": "smallcaps3 font, 0 spacing, star19 decoration", "charsets": "Supplemental Mathematical Operators,IPA Extensions,Mathematical Operators,Arabic,ASCII C0,ASCII C1,Latin Extended-B,Phonetic Extensions", "chartypes": "Letters,Symbols,Separators,Punctuations"}, {"caption": "`L\u2019art ASCII consiste \u00e0 r\u00e9aliser des images uniquement \u00e0 l'aide des lettres et caract\u00e8res sp\u00e9ciaux contenus dans le code ASCII.` in smallcaps3 font, with 3 spacing and no decoration", "content": "\u029f      \u1d00   \u0280   \u1d1b       \u1d00   s   \u1d04   \u026a   \u026a       \u1d04   \u1d0f   \u0274   s   \u026a   s   \u1d1b   \u1d07              \u0280      \u1d00   \u029f   \u026a   s   \u1d07   \u0280       \u1d05   \u1d07   s       \u026a   \u1d0d   \u1d00   \u0262   \u1d07   s       \u1d1c   \u0274   \u026a   \u01eb   \u1d1c   \u1d07   \u1d0d   \u1d07   \u0274   \u1d1b              \u029f   '   \u1d00   \u026a   \u1d05   \u1d07       \u1d05   \u1d07   s       \u029f   \u1d07   \u1d1b   \u1d1b   \u0280   \u1d07   s       \u1d07   \u1d1b       \u1d04   \u1d00   \u0280   \u1d00   \u1d04   \u1d1b      \u0280   \u1d07   s       s   \u1d18      \u1d04   \u026a   \u1d00   \u1d1c   x       \u1d04   \u1d0f   \u0274   \u1d1b   \u1d07   \u0274   \u1d1c   s       \u1d05   \u1d00   \u0274   s       \u029f   \u1d07       \u1d04   \u1d0f   \u1d05   \u1d07       \u1d00   s   \u1d04   \u026a   \u026a   .", "labels": "smallcaps3 font, 3 spacing, no decoration", "charsets": "Latin Extended-B,IPA Extensions,ASCII C0,Phonetic Extensions", "chartypes": "Letters,Separators,Punctuations"}, {"caption": "`L\u2019art ASCII consiste \u00e0 r\u00e9aliser des images uniquement \u00e0 l'aide des lettres et caract\u00e8res sp\u00e9ciaux contenus dans le code ASCII.` in smallcaps3 font, with 0 spacing and no decoration", "content": "\u029f\u1d00\u0280\u1d1b \u1d00s\u1d04\u026a\u026a \u1d04\u1d0f\u0274s\u026as\u1d1b\u1d07  \u0280\u1d00\u029f\u026as\u1d07\u0280 \u1d05\u1d07s \u026a\u1d0d\u1d00\u0262\u1d07s \u1d1c\u0274\u026a\u01eb\u1d1c\u1d07\u1d0d\u1d07\u0274\u1d1b  \u029f'\u1d00\u026a\u1d05\u1d07 \u1d05\u1d07s \u029f\u1d07\u1d1b\u1d1b\u0280\u1d07s \u1d07\u1d1b \u1d04\u1d00\u0280\u1d00\u1d04\u1d1b\u0280\u1d07s s\u1d18\u1d04\u026a\u1d00\u1d1cx \u1d04\u1d0f\u0274\u1d1b\u1d07\u0274\u1d1cs \u1d05\u1d00\u0274s \u029f\u1d07 \u1d04\u1d0f\u1d05\u1d07 \u1d00s\u1d04\u026a\u026a.", "labels": "smallcaps3 font, 0 spacing, no decoration", "charsets": "Latin Extended-B,IPA Extensions,ASCII C0,Phonetic Extensions", "chartypes": "Letters,Separators,Punctuations"}]